LICENSE
MANIFEST.in
README.md
requirements.txt
setup.py
robotframework_hardware_jim.egg-info/PKG-INFO
robotframework_hardware_jim.egg-info/SOURCES.txt
robotframework_hardware_jim.egg-info/dependency_links.txt
robotframework_hardware_jim.egg-info/requires.txt
robotframework_hardware_jim.egg-info/top_level.txt
src/HardwareLibrary/__init__.py
src/HardwareLibrary/version.py
src/HardwareLibrary/hardware/__init__.py
src/HardwareLibrary/hardware/interface/__init__.py
src/HardwareLibrary/hardware/moudle/__init__.py
src/HardwareLibrary/hardware/moudle/file.py
src/HardwareLibrary/hardware/moudle/system.py
src/HardwareLibrary/keywords/__init__.py
src/HardwareLibrary/keywords/file.py
src/HardwareLibrary/keywords/system.py