Metadata-Version: 2.1
Name: robotframework-hardware-jim
Version: 1.0.8
Summary: Support Command and GUI operation for Windows
Home-page: https://github.com/JimRevolutionist/robotframework-hardware
Author: HP
Author-email: jim.tang@hp.com
License: MIT
Platform: Windows
Classifier: Programming Language :: Python :: 3
Classifier: Programming Language :: Python :: 3.8
Classifier: Programming Language :: Python :: 3.9
Classifier: Programming Language :: Python :: 3.10
Classifier: License :: OSI Approved :: MIT License
Classifier: Operating System :: Microsoft
Classifier: Topic :: Software Development :: Testing
Classifier: Framework :: Robot Framework
Classifier: Framework :: Robot Framework :: Library
License-File: LICENSE
